.project
.pydevproject
MANIFEST.in
README.txt
build.sh
example_settings.py
setup.py
cabig/__init__.py
cabig/__init__.pyc
cabig/cacore/__init__.py
cabig/cacore/generate/__init__.py
cabig/cacore/generate/cacore2python.py
cabig/cacore/generate/commands.py
cabig/cacore/generate/domain.tmpl
cabig/cacore/generate/service.tmpl
cabig/cacore/ws/__init__.py
cabig/cacore/ws/axis.py
cabig/cacore/ws/proxy.py
pyCaCORE.egg-info/PKG-INFO
pyCaCORE.egg-info/SOURCES.txt
pyCaCORE.egg-info/dependency_links.txt
pyCaCORE.egg-info/entry_points.txt
pyCaCORE.egg-info/namespace_packages.txt
pyCaCORE.egg-info/requires.txt
pyCaCORE.egg-info/top_level.txt