Metadata-Version: 1.0
Name: pyCaCORE
Version: 0.2.0
Summary: caCORE Python API Generator
Home-page: http://cabioapi.nci.nih.gov/
Author: Konrad Rokicki
Author-email: rokickik@mail.nih.gov
License: caBIO Software License
Platform: All
